__init__.py
app/__init__.py
factory_py-0.0.2.dist-info/METADATA
factory_py-0.0.2.dist-info/WHEEL
factory_py-0.0.2.dist-info/top_level.txt
factory_py-0.0.2.dist-info/RECORD
